tyrone_mings/__init__.py
tyrone_mings/examples.py
tyrone_mings/fixtures.py
tyrone_mings/leaguesclubs.py
tyrone_mings/matches.py
tyrone_mings/players.py
tyrone_mings/tools.py
tyrone_mings/transfers.py
tyrone_mings-1.3.0.dist-info/METADATA
tyrone_mings-1.3.0.dist-info/WHEEL
tyrone_mings-1.3.0.dist-info/top_level.txt
tyrone_mings-1.3.0.dist-info/RECORD
