Metadata-Version: 2.1
Name: tyrone-mings
Version: 1.3.0
Summary: A package to help pull information from the transfermarkt website
Home-page: https://github.com/FCrSTATS/tyrone_mings
Author: FC rSTATS
Author-email: me@fcrstats.com
Classifier: Programming Language :: Python :: 3
Classifier: License :: OSI Approved :: MIT License
Classifier: Operating System :: OS Independent
Requires-Python: >=3.6
Requires-Dist: lxml (>=4.5.0)
Requires-Dist: requests (>=2.0.0)
Requires-Dist: bs4 (==0.0.1)
Requires-Dist: js2xml (==0.3.1)
Requires-Dist: pandas (>=0.23.4)
